sil/__init__.py
sil/sil.py
sil/utils.py
sil-0.1.6.dist-info/LICENSE
sil-0.1.6.dist-info/METADATA
sil-0.1.6.dist-info/WHEEL
sil-0.1.6.dist-info/top_level.txt
sil-0.1.6.dist-info/RECORD
