Metadata-Version: 2.1
Name: sil
Version: 0.1.6
Summary: Status indicator inline
Home-page: https://pypi.org/project/sil/
Author: Sumner Magruder
Author-email: sumner.magruder@zmnh.uni-hamburg.de
License: UNKNOWN
Platform: UNKNOWN
Classifier: Programming Language :: Python :: 3.6
Classifier: License :: OSI Approved :: MIT License
Classifier: Operating System :: OS Independent
